dbtrunner_dtacs/__init__.py
dbtrunner_dtacs/main.py
dbtrunner_dtacs-0.1.0.dist-info/LICENSE
dbtrunner_dtacs-0.1.0.dist-info/METADATA
dbtrunner_dtacs-0.1.0.dist-info/WHEEL
dbtrunner_dtacs-0.1.0.dist-info/RECORD
